
{
  "header": {
    "event": "Allocation failed - JavaScript heap out of memory",
    "trigger": "FatalError",
    "filename": "report.20200312.165324.29819.0.001.json",
    "dumpEventTime": "2020-03-12T16:53:24Z",
    "dumpEventTimeStamp": "1584003204011",
    "processId": 29819,
    "cwd": "/home/hooke/hooke.life.admin",
    "commandLine": [
      "/home/hooke/.nvm/versions/node/v11.15.0/bin/node",
      "/home/hooke/hooke.life.admin/node_modules/.bin/strapi",
      "build"
    ],
    "nodejsVersion": "v11.15.0",
    "glibcVersionRuntime": "2.17",
    "glibcVersionCompiler": "2.12",
    "wordSize": 64,
    "arch": "x64",
    "platform": "linux",
    "componentVersions": {
      "node": "11.15.0",
      "v8": "7.0.276.38-node.19",
      "uv": "1.27.0",
      "zlib": "1.2.11",
      "brotli": "1.0.7",
      "ares": "1.15.0",
      "modules": "67",
      "nghttp2": "1.37.0",
      "napi": "4",
      "llhttp": "1.1.1",
      "http_parser": "2.8.0",
      "openssl": "1.1.1b",
      "cldr": "34.0",
      "icu": "63.1",
      "tz": "2018e",
      "unicode": "11.0"
    },
    "release": {
      "name": "node",
      "headersUrl": "https://nodejs.org/download/release/v11.15.0/node-v11.15.0-headers.tar.gz",
      "sourceUrl": "https://nodejs.org/download/release/v11.15.0/node-v11.15.0.tar.gz"
    },
    "osName": "Linux",
    "osRelease": "3.10.0-1062.9.1.el7.x86_64",
    "osVersion": "#1 SMP Fri Dec 6 15:49:49 UTC 2019",
    "osMachine": "x86_64",
    "host": "VM_0_7_centos"
  },
  "javascriptStack": {
    "message": "No stack.",
    "stack": [
      "Unavailable."
    ]
  },
  "nativeStack": [
    {
      "pc": "0x0000000000a702fd",
      "symbol": "report::TriggerNodeReport(v8::Isolate*, node::Environment*, char const*, char const*, std::string const&, v8::Local<v8::String>) [/home/hooke/.nvm/versions/node/v11.15.0/bin/node]"
    },
    {
      "pc": "0x000000000095ccb3",
      "symbol": "node::OnFatalError(char const*, char const*) [/home/hooke/.nvm/versions/node/v11.15.0/bin/node]"
    },
    {
      "pc": "0x0000000000b3dbde",
      "symbol": "v8::Utils::ReportOOMFailure(v8::internal::Isolate*, char const*, bool) [/home/hooke/.nvm/versions/node/v11.15.0/bin/node]"
    },
    {
      "pc": "0x0000000000b3de14",
      "symbol": "v8::internal::V8::FatalProcessOutOfMemory(v8::internal::Isolate*, char const*, bool) [/home/hooke/.nvm/versions/node/v11.15.0/bin/node]"
    },
    {
      "pc": "0x0000000000f3ce52",
      "symbol": " [/home/hooke/.nvm/versions/node/v11.15.0/bin/node]"
    },
    {
      "pc": "0x0000000000f3cf58",
      "symbol": "v8::internal::Heap::CheckIneffectiveMarkCompact(unsigned long, double) [/home/hooke/.nvm/versions/node/v11.15.0/bin/node]"
    },
    {
      "pc": "0x0000000000f49678",
      "symbol": "v8::internal::Heap::PerformGarbageCollection(v8::internal::GarbageCollector, v8::GCCallbackFlags) [/home/hooke/.nvm/versions/node/v11.15.0/bin/node]"
    },
    {
      "pc": "0x0000000000f4a18b",
      "symbol": "v8::internal::Heap::CollectGarbage(v8::internal::AllocationSpace, v8::internal::GarbageCollectionReason, v8::GCCallbackFlags) [/home/hooke/.nvm/versions/node/v11.15.0/bin/node]"
    },
    {
      "pc": "0x0000000000f4cec1",
      "symbol": "v8::internal::Heap::AllocateRawWithRetryOrFail(int, v8::internal::AllocationSpace, v8::internal::AllocationAlignment) [/home/hooke/.nvm/versions/node/v11.15.0/bin/node]"
    },
    {
      "pc": "0x0000000000f170f4",
      "symbol": "v8::internal::Factory::NewFillerObject(int, bool, v8::internal::AllocationSpace) [/home/hooke/.nvm/versions/node/v11.15.0/bin/node]"
    },
    {
      "pc": "0x00000000011cd3fe",
      "symbol": "v8::internal::Runtime_AllocateInNewSpace(int, v8::internal::Object**, v8::internal::Isolate*) [/home/hooke/.nvm/versions/node/v11.15.0/bin/node]"
    },
    {
      "pc": "0x000017a93c34fc5d",
      "symbol": ""
    }
  ],
  "javascriptHeap": {
    "totalMemory": 280854528,
    "totalCommittedMemory": 278790192,
    "usedMemory": 259789160,
    "availableMemory": 28876200,
    "memoryLimit": 307088029,
    "heapSpaces": {
      "read_only_space": {
        "memorySize": 524288,
        "committedMemory": 42224,
        "capacity": 515584,
        "used": 33520,
        "available": 482064
      },
      "new_space": {
        "memorySize": 2097152,
        "committedMemory": 1274296,
        "capacity": 1031168,
        "used": 208320,
        "available": 822848
      },
      "old_space": {
        "memorySize": 231411712,
        "committedMemory": 230940904,
        "capacity": 222130032,
        "used": 220403992,
        "available": 1726040
      },
      "code_space": {
        "memorySize": 4718592,
        "committedMemory": 4431008,
        "capacity": 3822272,
        "used": 3822272,
        "available": 0
      },
      "map_space": {
        "memorySize": 7876608,
        "committedMemory": 7875584,
        "capacity": 2598480,
        "used": 2598480,
        "available": 0
      },
      "large_object_space": {
        "memorySize": 34226176,
        "committedMemory": 34226176,
        "capacity": 58567824,
        "used": 32722576,
        "available": 25845248
      },
      "new_large_object_space": {
        "memorySize": 0,
        "committedMemory": 0,
        "capacity": 0,
        "used": 0,
        "available": 0
      }
    }
  },
  "resourceUsage": {
    "userCpuSeconds": 44.7315,
    "kernelCpuSeconds": 1.40398,
    "cpuConsumptionPercent": 85.4361,
    "maxRss": 350380032,
    "pageFaults": {
      "IORequired": 6,
      "IONotRequired": 149094
    },
    "fsActivity": {
      "reads": 165184,
      "writes": 10992
    }
  },
  "uvthreadResourceUsage": {
    "userCpuSeconds": 28.5765,
    "kernelCpuSeconds": 0.933187,
    "cpuConsumptionPercent": 54.6476,
    "fsActivity": {
      "reads": 90760,
      "writes": 0
    }
  },
  "libuv": [
  ],
  "environmentVariables": {
    "NVM_INC": "/home/hooke/.nvm/versions/node/v11.15.0/include/node",
    "npm_package_engines_npm": ">=6.0.0",
    "npm_package_dependencies_strapi_utils": "3.0.0-beta.19.3",
    "XDG_SESSION_ID": "5337",
    "npm_package_dependencies_strapi_plugin_graphql": "3.0.0-beta.19.3",
    "HOSTNAME": "VM_0_7_centos",
    "NODE": "/home/hooke/.nvm/versions/node/v11.15.0/bin/node",
    "INIT_CWD": "/home/hooke/hooke.life.admin",
    "NVM_CD_FLAGS": "",
    "npm_config_version_git_tag": "true",
    "TERM": "xterm",
    "SHELL": "/bin/bash",
    "npm_package_dependencies_strapi": "3.0.0-beta.19.3",
    "HISTSIZE": "3000",
    "SSH_CLIENT": "114.118.30.32 57499 22",
    "npm_config_init_license": "MIT",
    "NODE_OPTIONS": "--max_old_space_size=256",
    "SSH_TTY": "/dev/pts/0",
    "npm_package_private": "true",
    "npm_config_registry": "https://registry.yarnpkg.com",
    "npm_config_home": "https://yarnpkg.com",
    "npm_package_readmeFilename": "README.md",
    "npm_package_dependencies_strapi_plugin_upload": "3.0.0-beta.19.3",
    "NVM_DIR": "/home/hooke/.nvm",
    "USER": "hooke",
    "npm_package_description": "A Strapi application",
    "LS_COLORS": "rs=0:di=01;34:ln=01;36:mh=00:pi=40;33:so=01;35:do=01;35:bd=40;33;01:cd=40;33;01:or=40;31;01:mi=01;05;37;41:su=37;41:sg=30;43:ca=30;41:tw=30;42:ow=34;42:st=37;44:ex=01;32:*.tar=01;31:*.tgz=01;31:*.arc=01;31:*.arj=01;31:*.taz=01;31:*.lha=01;31:*.lz4=01;31:*.lzh=01;31:*.lzma=01;31:*.tlz=01;31:*.txz=01;31:*.tzo=01;31:*.t7z=01;31:*.zip=01;31:*.z=01;31:*.Z=01;31:*.dz=01;31:*.gz=01;31:*.lrz=01;31:*.lz=01;31:*.lzo=01;31:*.xz=01;31:*.bz2=01;31:*.bz=01;31:*.tbz=01;31:*.tbz2=01;31:*.tz=01;31:*.deb=01;31:*.rpm=01;31:*.jar=01;31:*.war=01;31:*.ear=01;31:*.sar=01;31:*.rar=01;31:*.alz=01;31:*.ace=01;31:*.zoo=01;31:*.cpio=01;31:*.7z=01;31:*.rz=01;31:*.cab=01;31:*.jpg=01;35:*.jpeg=01;35:*.gif=01;35:*.bmp=01;35:*.pbm=01;35:*.pgm=01;35:*.ppm=01;35:*.tga=01;35:*.xbm=01;35:*.xpm=01;35:*.tif=01;35:*.tiff=01;35:*.png=01;35:*.svg=01;35:*.svgz=01;35:*.mng=01;35:*.pcx=01;35:*.mov=01;35:*.mpg=01;35:*.mpeg=01;35:*.m2v=01;35:*.mkv=01;35:*.webm=01;35:*.ogm=01;35:*.mp4=01;35:*.m4v=01;35:*.mp4v=01;35:*.vob=01;35:*.qt=01;35:*.nuv=01;35:*.wmv=01;35:*.asf=01;35:*.rm=01;35:*.rmvb=01;35:*.flc=01;35:*.avi=01;35:*.fli=01;35:*.flv=01;35:*.gl=01;35:*.dl=01;35:*.xcf=01;35:*.xwd=01;35:*.yuv=01;35:*.cgm=01;35:*.emf=01;35:*.axv=01;35:*.anx=01;35:*.ogv=01;35:*.ogx=01;35:*.aac=01;36:*.au=01;36:*.flac=01;36:*.mid=01;36:*.midi=01;36:*.mka=01;36:*.mp3=01;36:*.mpc=01;36:*.ogg=01;36:*.ra=01;36:*.wav=01;36:*.axa=01;36:*.oga=01;36:*.spx=01;36:*.xspf=01;36:",
    "npm_package_license": "MIT",
    "npm_config_npm": "set",
    "npm_package_strapi_uuid": "45dbf4d2-a4db-425e-8632-6696906fc2af",
    "npm_execpath": "/usr/lib/node_modules/yarn/bin/yarn.js",
    "npm_package_dependencies_sqlite3": "^4.1.1",
    "npm_package_author_name": "A Strapi developer",
    "MAIL": "/var/spool/mail/hooke",
    "PATH": "/tmp/yarn--1584003149008-0.1666817145070143:/home/hooke/hooke.life.admin/node_modules/.bin:/home/hooke/.config/yarn/link/node_modules/.bin:/home/hooke/.yarn/bin:/home/hooke/.nvm/versions/node/v11.15.0/libexec/lib/node_modules/npm/bin/node-gyp-bin:/home/hooke/.nvm/versions/node/v11.15.0/lib/node_modules/npm/bin/node-gyp-bin:/home/hooke/.nvm/versions/node/v11.15.0/bin/node_modules/npm/bin/node-gyp-bin:/home/hooke/.nvm/versions/node/v11.15.0/bin:/usr/local/bin:/usr/bin:/usr/local/sbin:/usr/sbin",
    "npm_config_argv": "{\"remain\":[],\"cooked\":[\"run\",\"build\"],\"original\":[\"build\"]}",
    "npm_package_scripts_develop": "strapi develop",
    "_": "/home/hooke/hooke.life.admin/node_modules/.bin/strapi",
    "PWD": "/home/hooke/hooke.life.admin",
    "npm_package_dependencies_strapi_admin": "3.0.0-beta.19.3",
    "npm_lifecycle_event": "build",
    "LANG": "en_US.utf8",
    "npm_package_name": "hooke-life",
    "npm_package_scripts_strapi": "strapi",
    "npm_package_dependencies_strapi_plugin_content_manager": "3.0.0-beta.19.3",
    "npm_package_scripts_build": "strapi build",
    "npm_package_scripts_start": "strapi start",
    "npm_config_version_commit_hooks": "true",
    "NODE_ENV": "production",
    "npm_config_bin_links": "true",
    "npm_package_engines_node": ">=10.0.0",
    "npm_package_version": "0.1.0",
    "SHLVL": "2",
    "HOME": "/home/hooke",
    "npm_config_save_prefix": "^",
    "npm_config_strict_ssl": "true",
    "npm_config_version_git_message": "v%s",
    "npm_package_dependencies_knex": "<0.20.0",
    "LOGNAME": "hooke",
    "YARN_WRAP_OUTPUT": "false",
    "npm_package_scripts_admin": "yarn develop --watch-admin",
    "npm_lifecycle_script": "strapi build",
    "npm_package_dependencies_strapi_plugin_users_permissions": "3.0.0-beta.19.3",
    "SSH_CONNECTION": "114.118.30.32 57499 172.27.0.7 22",
    "NVM_BIN": "/home/hooke/.nvm/versions/node/v11.15.0/bin",
    "LESSOPEN": "||/usr/bin/lesspipe.sh %s",
    "PROMPT_COMMAND": "history -a; printf \"\\033]0;%s@%s:%s\\007\" \"${USER}\" \"${HOSTNAME%%.*}\" \"${PWD/#$HOME/~}\"",
    "npm_config_version_git_sign": "",
    "npm_config_ignore_scripts": "",
    "npm_config_user_agent": "yarn/1.22.1 npm/? node/v11.15.0 linux x64",
    "npm_package_dependencies_strapi_plugin_email": "3.0.0-beta.19.3",
    "npm_package_dependencies_strapi_plugin_content_type_builder": "3.0.0-beta.19.3",
    "XDG_RUNTIME_DIR": "/run/user/1000",
    "npm_config_init_version": "1.0.0",
    "npm_config_ignore_optional": "",
    "HISTTIMEFORMAT": "%F %T ",
    "npm_package_dependencies_strapi_connector_bookshelf": "3.0.0-beta.19.3",
    "npm_node_execpath": "/home/hooke/.nvm/versions/node/v11.15.0/bin/node",
    "npm_config_version_tag_prefix": "v",
    "WEBPACK_DEV_SERVER": "true"
  },
  "userLimits": {
    "core_file_size_blocks": {
      "soft": 0,
      "hard": "unlimited"
    },
    "data_seg_size_kbytes": {
      "soft": "unlimited",
      "hard": "unlimited"
    },
    "file_size_blocks": {
      "soft": "unlimited",
      "hard": "unlimited"
    },
    "max_locked_memory_bytes": {
      "soft": 65536,
      "hard": 65536
    },
    "max_memory_size_kbytes": {
      "soft": "unlimited",
      "hard": "unlimited"
    },
    "open_files": {
      "soft": 100002,
      "hard": 100002
    },
    "stack_size_bytes": {
      "soft": 8388608,
      "hard": "unlimited"
    },
    "cpu_time_seconds": {
      "soft": "unlimited",
      "hard": "unlimited"
    },
    "max_user_processes": {
      "soft": 3878,
      "hard": 3878
    },
    "virtual_memory_kbytes": {
      "soft": "unlimited",
      "hard": "unlimited"
    }
  },
  "sharedObjects": [
    "/lib64/libdl.so.2",
    "/lib64/librt.so.1",
    "/lib64/libstdc++.so.6",
    "/lib64/libm.so.6",
    "/lib64/libgcc_s.so.1",
    "/lib64/libpthread.so.0",
    "/lib64/libc.so.6",
    "/lib64/ld-linux-x86-64.so.2"
  ]
}